api_bulk/__init__.py
api_bulk/cant_use_.py
api_bulk/fix_bug_.py
api_bulk/sandbox1_.py
api_bulk/utils_play_audio_file.py
music_riff/__init__.py
music_riff/cant_use_.py
music_riff/fix_bug_.py
music_riff/sandbox1_.py
music_riff/utils_.py
package_name/__init__.py
package_name/cant_use_.py
package_name/fix_bug_.py
package_name/sandbox1_.py
package_name/utils_.py
play_audio/__init__.py
play_audio/cant_use_.py
play_audio/fix_bug_.py
play_audio/sandbox1_.py
play_audio/utils_.py
play_audio_file/__init__.py
play_audio_file/cant_use_.py
play_audio_file/fix_bug_.py
play_audio_file/sandbox1_.py
play_audio_file/utils_play_audio_file.py
riff_music/__init__.py
riff_music/cant_use_.py
riff_music/fix_bug_.py
riff_music/sandbox1_.py
riff_music/utils_riff.py
api_bulk-0.1.0rc1.dist-info/LICENSE
api_bulk-0.1.0rc1.dist-info/METADATA
api_bulk-0.1.0rc1.dist-info/WHEEL
api_bulk-0.1.0rc1.dist-info/top_level.txt
api_bulk-0.1.0rc1.dist-info/RECORD
