Metadata-Version: 2.1
Name: api_bulk
Version: 0.1.0rc1
Summary: different api bulk tools
Author: Norathee Lert
License: MIT
License-File: LICENSE
Requires-Dist: pandas
Requires-Dist: os-toolkit >=0.1.1
Requires-Dist: py-string-tool >=0.1.3
Requires-Dist: python-wizard >=0.1.1
Requires-Dist: play-audio-file >=0.1.0
